oresat_tpane/__init__.py
oresat_tpane/datagrid.py
oresat_tpane/pane.py
tests/__init__.py
tests/spec_hello_world.py
oresat_tpane-1.0.0.dist-info/LICENSE
oresat_tpane-1.0.0.dist-info/METADATA
oresat_tpane-1.0.0.dist-info/WHEEL
oresat_tpane-1.0.0.dist-info/top_level.txt
oresat_tpane-1.0.0.dist-info/RECORD
