Metadata-Version: 2.1
Name: oresat-tpane
Version: 1.0.0
Summary: This module is responsible for providing a high-level interface for elements of Curses UI and general user interaction with the app
Home-page: https://github.com/oresat/oresat-tpane
Author: Dmitri McGuckin
Maintainer: Portland State Aerospace Society
Maintainer-email: oresat@pdx.edu
License: GPL-3.0
Project-URL: Documentation, https://canopen-monitor.readthedocs.io
Project-URL: Bug Tracking, https://github.com/oresat/oresat-tpane/labels/bug
Platform: UNKNOWN
Classifier: Programming Language :: Python :: 3
Classifier: License :: OSI Approved :: GNU General Public License v3 (GPLv3)
Classifier: Operating System :: OS Independent
Classifier: Environment :: Console :: Curses
Classifier: Topic :: Scientific/Engineering :: Information Analysis
Classifier: Topic :: Software Development :: User Interfaces
Requires-Python: >=3.9.0
License-File: LICENSE
Requires-Dist: urwid (==2.1.2)
Provides-Extra: dev
Requires-Dist: python-can ; extra == 'dev'
Requires-Dist: setuptools ; extra == 'dev'
Requires-Dist: wheel ; extra == 'dev'
Requires-Dist: flake8 ; extra == 'dev'
Requires-Dist: twine ; extra == 'dev'
Requires-Dist: sphinx ; extra == 'dev'
Requires-Dist: sphinx-rtd-theme ; extra == 'dev'
